tasch/__init__.py
tasch-0.2.5.dist-info/WHEEL
tasch-0.2.5.dist-info/METADATA
tasch-0.2.5.dist-info/RECORD
