Metadata-Version: 2.1
Name: tasch
Version: 0.2.5
Summary: An advanced calculator
Author: jscz
Requires-Python: >=3.10,<4.0
Classifier: Programming Language :: Python :: 3
Classifier: Programming Language :: Python :: 3.10
